[
    {
		"timestamp": "2023-07-06T22:55:13.242165Z",
		"sensor": "88fa6696997b",
		"type": "Cowrie",
		"message": "Connection lost after 120 seconds",
		"t-pot_ip_ext": "40.76.178.241",
		"session": "7d58b0631b4c",
		"host": "4b2c8c0db01d",
		"username": "ubnt",
		"password": "ubnt",
		"input": "enable",
		"protocol": "telnet",
		"size": 3173,
		"ip_rep": "known attacker",
		"t-pot_ip_int": "10.0.2.4",
		"arch": "linux-am33-lsb",
		"shasum": "19bd3cf85b72114d5b4c8e31b3c91d722dc6ac92ada67cbdd467bef95cb6d08c",
		"ttylog": "log/tty/19bd3cf85b72114d5b4c8e31b3c91d722dc6ac92ada67cbdd467bef95cb6d08c",
		"hassh": "1616c6d18e845e7a01168a44591f7a35",
		"hasshAlgorithms": "ecdh-sha2-nistp256,ecdh-sha2-nistp384,ecdh-sha2-nistp521,diffie-hellman-group-exchange-sha256,diffie-hellman-group-exchange-sha1,diffie-hellman-group14-sha1,diffie-hellman-group1-sha1;aes128-ctr,aes192-ctr,aes256-ctr,aes256-cbc,rijndael-cbc@lysator.liu.se,aes192-cbc,aes128-cbc,blowfish-cbc,arcfour128,arcfour,cast128-cbc,3des-cbc;hmac-sha2-256,hmac-sha2-512,hmac-sha1,hmac-sha1-96,hmac-md5,hmac-md5-96,hmac-ripemd160,hmac-ripemd160@openssh.com;none",
		"kexAlgs": [
			"ecdh-sha2-nistp256",
			"ecdh-sha2-nistp384",
			"ecdh-sha2-nistp521",
			"diffie-hellman-group-exchange-sha256",
			"diffie-hellman-group-exchange-sha1",
			"diffie-hellman-group14-sha1",
			"diffie-hellman-group1-sha1"
		],
		"macCS": [
			"hmac-sha2-256",
			"hmac-sha2-512",
			"hmac-sha1",
			"hmac-sha1-96",
			"hmac-md5",
			"hmac-md5-96",
			"hmac-ripemd160",
			"hmac-ripemd160@openssh.com"
		],
		"compCS": [
			"none"
		],
		"encCS": [
			"aes128-ctr",
			"aes192-ctr",
			"aes256-ctr",
			"aes256-cbc",
			"rijndael-cbc@lysator.liu.se",
			"aes192-cbc",
			"aes128-cbc",
			"blowfish-cbc",
			"arcfour128",
			"arcfour",
			"cast128-cbc",
			"3des-cbc"
		],
		"langCS": [
			""
		],
		"dest_ip": "172.25.0.2",
		"dest_port": 23,
		"duplicate": false,
		"src_port": 40334,
		"geoip": {
			"timezone": "Asia/Seoul",
			"region_name": "Gyeongsangnam-do",
			"region_code": "48",
			"location": {
				"lat": 35.3447,
				"lon": 129.0299
			},
			"continent_code": "AS",
			"country_name": "South Korea",
			"country_code2": "KR",
			"postal_code": "505",
			"as_org": "LG HelloVision Corp.",
			"ip": "119.149.246.205",
			"asn": 10066,
			"latitude": 35.3447,
			"city_name": "Yangsan",
			"country_code3": "KR",
			"longitude": 129.0299
		},
		"t-pot_hostname": "tragicsaw",
		"src_ip": "119.149.246.205",
		"geoip_ext": {
			"timezone": "America/New_York",
			"region_name": "Virginia",
			"region_code": "VA",
			"location": {
				"lat": 37.9273,
				"lon": -76.8545
			},
			"continent_code": "NA",
			"country_name": "United States",
			"country_code2": "US",
			"postal_code": "22560",
			"dma_code": 556,
			"as_org": "MICROSOFT-CORP-MSN-AS-BLOCK",
			"ip": "40.76.178.241",
			"asn": 8075,
			"latitude": 37.9273,
			"city_name": "Tappahannock",
			"country_code3": "US",
			"longitude": -76.8545
		},
		"duration": 120.02484321594238,
		"eventid": "cowrie.session.closed",
		"path": "/data/cowrie/log/cowrie.json",
		"version": "GET / HTTP/1.0"
    }
]